{
  "strategy": "default",
  "cedictPath": "./cedict_ts.u8",
  "matchStrategy": "prefix",
  "fuzzyMatch": true,
  "matchingWithoutEmoji": true,
  "treatAccentDiacriticsAsAlphabeticCharacters": false,
  "maxNumberOfSuggestions": 5,
  "maxNumberOfWordsAsPhrase": 3,
  "minNumberOfCharactersTriggered": 0,
  "minNumberOfWordsTriggeredPhrase": 1,
  "complementAutomatically": true,
  "delayMilliSeconds": 0,
  "disableSuggestionsDuringImeOn": false,
  "insertAfterCompletion": true,
  "firstCharactersDisableSuggestions": ":/^",
  "useCommonPrefixCompletionOfSuggestion": false,
  "patternsToSuppressTrigger": [
    "^~~~.*",
    "^```.*"
  ],
  "showMatchStrategy": true,
  "showComplementAutomatically": true,
  "showIndexingStatus": true,
  "descriptionOnSuggestion": "Short",
  "selectSuggestionKeys": "Enter",
  "additionalCycleThroughSuggestionsKeys": "None",
  "disableUpDownKeysForCycleThroughSuggestionsKeys": false,
  "openSourceFileKey": "None",
  "propagateEsc": false,
  "enableCurrentFileComplement": true,
  "currentFileMinNumberOfCharacters": 0,
  "onlyComplementEnglishOnCurrentFileComplement": false,
  "enableCurrentVaultComplement": false,
  "currentVaultMinNumberOfCharacters": 0,
  "includeCurrentVaultPathPrefixPatterns": "",
  "excludeCurrentVaultPathPrefixPatterns": "",
  "includeCurrentVaultOnlyFilesUnderCurrentDirectory": false,
  "enableCustomDictionaryComplement": false,
  "customDictionaryPaths": "https://raw.githubusercontent.com/first20hours/google-10000-english/master/google-10000-english-no-swears.txt",
  "columnDelimiter": "Tab",
  "customDictionaryWordRegexPattern": "",
  "delimiterToHideSuggestion": "",
  "delimiterToDivideSuggestionsForDisplayFromInsertion": "",
  "caretLocationSymbolAfterComplement": "",
  "displayedTextSuffix": " => ...",
  "enableInternalLinkComplement": true,
  "suggestInternalLinkWithAlias": false,
  "excludeInternalLinkPathPrefixPatterns": "",
  "updateInternalLinksOnSave": true,
  "insertAliasTransformedFromDisplayedInternalLink": {
    "enabled": false,
    "beforeRegExp": "",
    "after": ""
  },
  "enableFrontMatterComplement": true,
  "frontMatterComplementMatchStrategy": "inherit",
  "insertCommaAfterFrontMatterCompletion": false,
  "intelligentSuggestionPrioritization": {
    "maxDaysToKeepHistory": 30,
    "maxNumberOfHistoryToKeep": 0
  },
  "disableOnMobile": false,
  "showLogAboutPerformanceInConsole": false,
  "selectionHistoryTree": {
    "DataLoader": {
      "DataLoader": {
        "currentFile": {
          "count": 2,
          "lastUpdated": 1681030088027
        }
      }
    },
    "LatexEquationManual": {
      "LatexEquationManual": {
        "internalLink": {
          "count": 1,
          "lastUpdated": 1681029978888
        }
      }
    },
    " data in enumerate": {
      " data in enumerate": {
        "currentFile": {
          "count": 1,
          "lastUpdated": 1681030012853
        }
      }
    },
    "ResNet": {
      "ResNet": {
        "currentFile": {
          "count": 1,
          "lastUpdated": 1681044322692
        }
      }
    },
    "ResNet：Kaiming": {
      "ResNet：Kaiming": {
        "currentFile": {
          "count": 1,
          "lastUpdated": 1681046255466
        }
      }
    },
    "train_": {
      "train_": {
        "currentFile": {
          "count": 1,
          "lastUpdated": 1681046961540
        }
      }
    },
    "uni-app": {
      "uni-app": {
        "internalLink": {
          "count": 1,
          "lastUpdated": 1681634949176
        },
        "currentFile": {
          "count": 1,
          "lastUpdated": 1681634974120
        }
      }
    },
    "api": {
      "api": {
        "internalLink": {
          "count": 1,
          "lastUpdated": 1681820252015
        }
      }
    },
    " 指令，它实际上是上述操作的语法糖：": {
      " 指令，它实际上是上述操作的语法糖：": {
        "currentFile": {
          "count": 2,
          "lastUpdated": 1681822045599
        }
      }
    },
    "input": {
      "input": {
        "currentFile": {
          "count": 1,
          "lastUpdated": 1681822097947
        }
      }
    },
    "v-model": {
      "v-model": {
        "currentFile": {
          "count": 1,
          "lastUpdated": 1681822105293
        }
      }
    },
    "html#key": {
      "html#key": {
        "currentFile": {
          "count": 1,
          "lastUpdated": 1681991638086
        }
      }
    },
    "1表格增删": {
      "1表格增删": {
        "currentFile": {
          "count": 1,
          "lastUpdated": 1681994402907
        }
      }
    },
    "component": {
      "component": {
        "currentFile": {
          "count": 1,
          "lastUpdated": 1681996214862
        }
      }
    }
  }
}